zcm/actor.py
zcm/test_components.py
zcm/subscriber.py
zcm/server.py
zcm/__init__.py
zcm/timer.py
zcm/component.py
zcm/client.py
zcm/operation_queue.py
zcm/publisher.py
zcm-1.0.0.dist-info/metadata.json
zcm-1.0.0.dist-info/WHEEL
zcm-1.0.0.dist-info/top_level.txt
zcm-1.0.0.dist-info/RECORD
zcm-1.0.0.dist-info/entry_points.txt
zcm-1.0.0.dist-info/DESCRIPTION.rst
zcm-1.0.0.dist-info/METADATA
