Metadata-Version: 2.0
Name: zcm
Version: 1.0.0
Summary: A lightweight component model using ZeroMQ
Home-page: https://github.com/pranav-srinivas-kumar/python-zcm
Author: Pranav Srinivas Kumar
Author-email: pranav.srinivas.kumar@gmail.com
License: MIT
Keywords: zeroMQ component actor models protobuf
Platform: UNKNOWN
Classifier: Development Status :: 5 - Production/Stable
Classifier: Intended Audience :: Developers
Classifier: Topic :: Software Development
Classifier: License :: OSI Approved :: MIT License
Classifier: Programming Language :: Python :: 2.7
Requires-Dist: pyzmq
Provides-Extra: dev
Requires-Dist: check-manifest; extra == 'dev'
Provides-Extra: test
Requires-Dist: coverage; extra == 'test'
